s3_parquetifier/__init__.py
s3_parquetifier/models.py
test/__init__.py
test/test_s3_parquetifier.py
s3_parquetifier-0.2.dist-info/LICENCE
s3_parquetifier-0.2.dist-info/METADATA
s3_parquetifier-0.2.dist-info/WHEEL
s3_parquetifier-0.2.dist-info/top_level.txt
s3_parquetifier-0.2.dist-info/RECORD
