Metadata-Version: 2.1
Name: s3-parquetifier
Version: 0.2
Summary: ETL job from CSV to Parquet in AWS S3
Home-page: https://github.com/Orfium/s3-parquetifier
Author: Konstantinos Siaterlis, John Economidis
Author-email: siaterliskonsta@gmail.com, johnnyecon@gmail.com
License: LICENSE
Platform: UNKNOWN
Requires-Dist: boto3
Requires-Dist: pandas
Requires-Dist: fastparquet
Requires-Dist: python-snappy
Requires-Dist: requests
Requires-Dist: wget
